Metadata-Version: 2.1
Name: pyannote.features.shennong
Version: 0.1
Summary: A feature extraction extension for the pyannote framework
Home-page: https://github.com/bootphon/pyannote-shennong-features
Author: Hadrien Titeux (CoML)
Author-email: hadrien.titeux@ens.fr
License: UNKNOWN
Platform: UNKNOWN
Classifier: Development Status :: 4 - Beta
Classifier: Intended Audience :: Science/Research
Classifier: License :: OSI Approved :: MIT License
Classifier: Natural Language :: English
Classifier: Programming Language :: Python :: 3
Classifier: Programming Language :: Python :: 3.6
Classifier: Programming Language :: Python :: 3.7
Classifier: Topic :: Scientific/Engineering
